shimmer/__init__.py
shimmer/alignment.py
shimmer/components/__init__.py
shimmer/components/box.py
shimmer/components/box_layout.py
shimmer/components/box_track_cursor.py
shimmer/components/draggable_box.py
shimmer/components/drawing.py
shimmer/components/focus.py
shimmer/components/font.py
shimmer/components/mouse_box.py
shimmer/components/pop_up.py
shimmer/components/selection.py
shimmer/components/sprite_box.py
shimmer/data_structures.py
shimmer/helpers.py
shimmer/inspections.py
shimmer/keyboard.py
shimmer/log_utils.py
shimmer/primitives.py
shimmer/programmable/__init__.py
shimmer/programmable/code_block.py
shimmer/programmable/if_elif.py
shimmer/programmable/instruction.py
shimmer/programmable/logic/__init__.py
shimmer/programmable/logic/base.py
shimmer/programmable/logic/definition.py
shimmer/widgets/__init__.py
shimmer/widgets/button.py
shimmer/widgets/close_button.py
shimmer/widgets/dialogs/__init__.py
shimmer/widgets/dialogs/base_dialog_window.py
shimmer/widgets/dialogs/common_dialogs.py
shimmer/widgets/dialogs/multiple_choice.py
shimmer/widgets/dialogs/text_input.py
shimmer/widgets/multiple_choice_buttons.py
shimmer/widgets/question_definition.py
shimmer/widgets/text_box.py
shimmer/widgets/window.py
shimmer-1.8.0.dist-info/LICENSE
shimmer-1.8.0.dist-info/WHEEL
shimmer-1.8.0.dist-info/METADATA
shimmer-1.8.0.dist-info/RECORD
