Metadata-Version: 2.1
Name: shimmer
Version: 1.8.0
Summary: Create games in python, without hassle - batteries included!
Home-page: https://github.com/MartinHowarth/shimmer
License: MIT
Keywords: game,framework,graphics
Author: Martin Howarth
Author-email: howarth.martin@gmail.com
Requires-Python: >=3.8,<4.0
Classifier: License :: OSI Approved :: MIT License
Classifier: Programming Language :: Python :: 3
Classifier: Programming Language :: Python :: 3.8
Requires-Dist: cocos2d (>=0.6.7,<0.7.0)
Requires-Dist: janus (>=0.4.0,<0.5.0)
Requires-Dist: more-itertools (>=8.0.2,<9.0.0)
Requires-Dist: pyglet (==1.4.3)
Requires-Dist: toml (>=0.9,<0.10)
Project-URL: Repository, https://github.com/MartinHowarth/shimmer
